beatstoch/__init__.py
beatstoch/bpm.py
beatstoch/cli.py
beatstoch/generator.py
beatstoch-1.5.2.dist-info/licenses/LICENSE
beatstoch-1.5.2.dist-info/METADATA
beatstoch-1.5.2.dist-info/WHEEL
beatstoch-1.5.2.dist-info/entry_points.txt
beatstoch-1.5.2.dist-info/top_level.txt
beatstoch-1.5.2.dist-info/RECORD
