Metadata-Version: 2.4
Name: beatstoch
Version: 1.5.2
Summary: BPM-aware stochastic drum generator: library + CLI.
Author: James Campbell
License-Expression: Unlicense
Project-URL: Homepage, https://github.com/james-see/beatstoch
Project-URL: Repository, https://github.com/james-see/beatstoch
Project-URL: Documentation, https://james-see.github.io/beatstoch/
Project-URL: Source, https://github.com/james-see/beatstoch
Project-URL: Tracker, https://github.com/james-see/beatstoch/issues
Keywords: midi,drums,music,bpm,stochastic,algorithmic,composition,audio,cli
Classifier: Development Status :: 5 - Production/Stable
Classifier: Intended Audience :: Developers
Classifier: Intended Audience :: End Users/Desktop
Classifier: Operating System :: OS Independent
Classifier: Programming Language :: Python :: 3
Classifier: Programming Language :: Python :: 3.9
Classifier: Programming Language :: Python :: 3.10
Classifier: Programming Language :: Python :: 3.11
Classifier: Programming Language :: Python :: 3.12
Classifier: Programming Language :: Python :: 3.13
Classifier: Programming Language :: Python :: 3.14
Classifier: Topic :: Multimedia :: Sound/Audio :: MIDI
Classifier: Topic :: Artistic Software
Classifier: Topic :: Software Development :: Libraries :: Python Modules
Requires-Python: >=3.9
License-File: LICENSE
Requires-Dist: mido>=1.3.0
Requires-Dist: numpy>=1.24.0
Requires-Dist: requests>=2.31.0
Requires-Dist: beautifulsoup4>=4.12.0
Dynamic: license-file
